stompman/__init__.py
stompman/client.py
stompman/config.py
stompman/connection.py
stompman/connection_lifespan.py
stompman/connection_manager.py
stompman/errors.py
stompman/frames.py
stompman/logger.py
stompman/py.typed
stompman/serde.py
stompman/subscription.py
stompman/transaction.py
stompman-3.9.0.dist-info/METADATA
stompman-3.9.0.dist-info/WHEEL
stompman-3.9.0.dist-info/RECORD
