Metadata-Version: 2.4
Name: stompman
Version: 3.9.0
Summary: Python STOMP client with pleasant API
Project-URL: repository, https://github.com/community-of-python/stompman
Author-email: Lev Vereshchagin <mail@vrslev.com>
License: MIT
Keywords: activemq,artemis,jms,messaging,stomp
Classifier: Development Status :: 4 - Beta
Classifier: Natural Language :: English
Classifier: Programming Language :: Python :: Implementation :: CPython
Classifier: Topic :: System :: Networking
Classifier: Typing :: Typed
Requires-Python: >=3.11
